MANIFEST.in
README.md
setup.py
CassandraLauncher.egg-info/PKG-INFO
CassandraLauncher.egg-info/SOURCES.txt
CassandraLauncher.egg-info/dependency_links.txt
CassandraLauncher.egg-info/requires.txt
CassandraLauncher.egg-info/top_level.txt
cassandralauncher/__init__.py
cassandralauncher/cassandralauncher.py
cassandralauncher/clusterlauncher.conf
cassandralauncher/clusterlauncher.py
cassandralauncher/common.py
cassandralauncher/datastax_pssh
cassandralauncher/datastax_s3_restore
cassandralauncher/datastax_s3_store
cassandralauncher/datastax_ssh
cassandralauncher/ec2.py
cassandralauncher/rax.py
cassandralauncher/s3cfg
scripts/cassandralauncher
scripts/imagelauncher