Metadata-Version: 1.0
Name: CassandraLauncher
Version: 1.19-0
Summary: Command line utilities for launching Cassandra clusters in EC2
Home-page: http://www.github.com/joaquincasares/cassandralauncher
Author: Joaquin Casares
Author-email: joaquin.casares AT gmail.com
License: UNKNOWN
Keywords: apache cassandra solr pig hive hadoop search analytics datastax cluster clustertools cloud cloudservers rackspace ec2 aws on-demand
Platform: UNKNOWN
